dwas/__init__.py
dwas/__main__.py
dwas/_config.py
dwas/_dependency_injection.py
dwas/_exceptions.py
dwas/_frontend.py
dwas/_inspect.py
dwas/_io.py
dwas/_logging.py
dwas/_pipeline.py
dwas/_runners.py
dwas/_scheduler.py
dwas/_subproc.py
dwas/_timing.py
dwas/py.typed
dwas/_steps/__init__.py
dwas/_steps/handlers.py
dwas/_steps/parametrize.py
dwas/_steps/registration.py
dwas/_steps/steps.py
dwas/predefined/__init__.py
dwas/predefined/_black.py
dwas/predefined/_coverage.py
dwas/predefined/_docformatter.py
dwas/predefined/_isort.py
dwas/predefined/_mypy.py
dwas/predefined/_package.py
dwas/predefined/_pylint.py
dwas/predefined/_pytest.py
dwas/predefined/_ruff.py
dwas/predefined/_sphinx.py
dwas/predefined/_twine.py
dwas/predefined/_unimport.py
dwas-0.0.5.dist-info/LICENSE
dwas-0.0.5.dist-info/METADATA
dwas-0.0.5.dist-info/WHEEL
dwas-0.0.5.dist-info/entry_points.txt
dwas-0.0.5.dist-info/top_level.txt
dwas-0.0.5.dist-info/RECORD
