Metadata-Version: 2.1
Name: dwas
Version: 0.0.5
Summary: dwas is a command line tool to define and run your development workflows
Author-email: Benjamin Schubert <contact@benschubert.me>
License: MIT
Project-URL: homepage, https://github.com/BenjaminSchubert/dwas
Project-URL: repository, https://github.com/BenjaminSchubert/dwas
Project-URL: tracker, https://github.com/BenjaminSchubert/dwas/issues
Project-URL: documentation, https://dwas.readthedocs.io/en/latest/
Project-URL: changelog, https://github.com/BenjaminSchubert/dwas/CHANGELOG.rst
Keywords: workflows,virtual,environments,isolated,testing
Classifier: Development Status :: 2 - Pre-Alpha
Classifier: Intended Audience :: Developers
Classifier: License :: OSI Approved :: MIT License
Classifier: Programming Language :: Python :: 3.8
Classifier: Programming Language :: Python :: 3.9
Classifier: Programming Language :: Python :: 3.10
Classifier: Programming Language :: Python :: 3.11
Classifier: Programming Language :: Python :: 3.12
Classifier: Programming Language :: Python :: 3.13
Classifier: Programming Language :: Python :: Implementation :: CPython
Classifier: Programming Language :: Python :: Implementation :: PyPy
Classifier: Topic :: Software Development :: Testing
Classifier: Topic :: Utilities
Requires-Python: >=3.8
License-File: LICENSE
Requires-Dist: colorama
Requires-Dist: virtualenv
Provides-Extra: docs
Requires-Dist: furo; extra == "docs"
Requires-Dist: sphinx; extra == "docs"
Requires-Dist: sphinxcontrib-spelling; extra == "docs"
Requires-Dist: sphinx-copybutton; extra == "docs"
Requires-Dist: sphinx-inline-tabs; extra == "docs"
Requires-Dist: pygments-ansi-color; extra == "docs"
Provides-Extra: test
Requires-Dist: pytest; extra == "test"
Requires-Dist: pytest-cov; extra == "test"
Requires-Dist: pytest-xdist; extra == "test"
Requires-Dist: pygments; extra == "test"
